{"hash":"57419d9de2344562a7a5","version":"5.50.0","time":3800,"builtAt":1629309712612,"publicPath":"auto","outputPath":"/home/stefan/Documents/Proyectos/interactive-pricing-component-main/dist","assetsByChunkName":{"main":["assets/main.f8a10ad495058f9c62a8.css","main5a95294ea625ccfbcba9.js"]},"assets":[{"type":"asset","name":"assets/images/desktop-version.png","size":53753,"emitted":true,"comparedForEmit":false,"cached":false,"info":{"copied":true,"sourceFilename":"images/desktop-version.png","size":53753},"chunkNames":[],"chunkIdHints":[],"auxiliaryChunkNames":[],"auxiliaryChunkIdHints":[],"related":{},"chunks":[],"auxiliaryChunks":[],"isOverSizeLimit":false},{"type":"asset","name":"assets/images/mobile-version.png","size":33008,"emitted":true,"comparedForEmit":false,"cached":false,"info":{"copied":true,"sourceFilename":"images/mobile-version.png","size":33008},"chunkNames":[],"chunkIdHints":[],"auxiliaryChunkNames":[],"auxiliaryChunkIdHints":[],"related":{},"chunks":[],"auxiliaryChunks":[],"isOverSizeLimit":false},{"type":"asset","name":"assets/main.f8a10ad495058f9c62a8.css","size":3007,"emitted":true,"comparedForEmit":false,"cached":false,"info":{"immutable":true,"contenthash":"f8a10ad495058f9c62a8","minimized":true,"size":3007},"chunkNames":["main"],"chunkIdHints":[],"auxiliaryChunkNames":[],"auxiliaryChunkIdHints":[],"related":{},"chunks":[179],"auxiliaryChunks":[],"isOverSizeLimit":false},{"type":"asset","name":"./index.html","size":1942,"emitted":true,"comparedForEmit":false,"cached":false,"info":{"size":1942},"chunkNames":[],"chunkIdHints":[],"auxiliaryChunkNames":[],"auxiliaryChunkIdHints":[],"related":{},"chunks":[],"auxiliaryChunks":[],"isOverSizeLimit":false},{"type":"asset","name":"assets/images/favicon-32x32.png","size":1063,"emitted":true,"comparedForEmit":false,"cached":false,"info":{"copied":true,"sourceFilename":"images/favicon-32x32.png","size":1063},"chunkNames":[],"chunkIdHints":[],"auxiliaryChunkNames":[],"auxiliaryChunkIdHints":[],"related":{},"chunks":[],"auxiliaryChunks":[],"isOverSizeLimit":false},{"type":"asset","name":"main5a95294ea625ccfbcba9.js","size":654,"emitted":true,"comparedForEmit":false,"cached":false,"info":{"immutable":true,"contenthash":"5a95294ea625ccfbcba9","javascriptModule":false,"minimized":true,"size":654},"chunkNames":["main"],"chunkIdHints":[],"auxiliaryChunkNames":[],"auxiliaryChunkIdHints":[],"related":{},"chunks":[179],"auxiliaryChunks":[],"isOverSizeLimit":false},{"type":"asset","name":"assets/images/icon-slider.svg","size":302,"emitted":true,"comparedForEmit":false,"cached":false,"info":{"copied":true,"sourceFilename":"images/icon-slider.svg","size":302},"chunkNames":[],"chunkIdHints":[],"auxiliaryChunkNames":[],"auxiliaryChunkIdHints":[],"related":{},"chunks":[],"auxiliaryChunks":[],"isOverSizeLimit":false},{"type":"asset","name":"9f6ed14bb3b0084b05a9.svg","size":196,"emitted":true,"comparedForEmit":false,"cached":false,"info":{"sourceFilename":"images/pattern-circles.svg","immutable":true,"contenthash":"9f6ed14bb3b0084b05a9","size":196},"chunkNames":[],"chunkIdHints":[],"auxiliaryChunkNames":["main"],"auxiliaryChunkIdHints":[],"related":{},"chunks":[],"auxiliaryChunks":[179],"isOverSizeLimit":false},{"type":"asset","name":"assets/images/pattern-circles.svg","size":196,"emitted":true,"comparedForEmit":false,"cached":false,"info":{"copied":true,"sourceFilename":"images/pattern-circles.svg","size":196},"chunkNames":[],"chunkIdHints":[],"auxiliaryChunkNames":[],"auxiliaryChunkIdHints":[],"related":{},"chunks":[],"auxiliaryChunks":[],"isOverSizeLimit":false},{"type":"asset","name":"76d3fa7ddce078ad96b5.svg","size":170,"emitted":true,"comparedForEmit":false,"cached":false,"info":{"sourceFilename":"images/bg-pattern.svg","immutable":true,"contenthash":"76d3fa7ddce078ad96b5","size":170},"chunkNames":[],"chunkIdHints":[],"auxiliaryChunkNames":["main"],"auxiliaryChunkIdHints":[],"related":{},"chunks":[],"auxiliaryChunks":[179],"isOverSizeLimit":false},{"type":"asset","name":"assets/images/bg-pattern.svg","size":170,"emitted":true,"comparedForEmit":false,"cached":false,"info":{"copied":true,"sourceFilename":"images/bg-pattern.svg","size":170},"chunkNames":[],"chunkIdHints":[],"auxiliaryChunkNames":[],"auxiliaryChunkIdHints":[],"related":{},"chunks":[],"auxiliaryChunks":[],"isOverSizeLimit":false},{"type":"asset","name":"83c38a48815855ecc2d7.svg","size":153,"emitted":true,"comparedForEmit":false,"cached":false,"info":{"sourceFilename":"images/icon-check.svg","immutable":true,"contenthash":"83c38a48815855ecc2d7","size":153},"chunkNames":[],"chunkIdHints":[],"auxiliaryChunkNames":["main"],"auxiliaryChunkIdHints":[],"related":{},"chunks":[],"auxiliaryChunks":[179],"isOverSizeLimit":false},{"type":"asset","name":"assets/images/icon-check.svg","size":153,"emitted":true,"comparedForEmit":false,"cached":false,"info":{"copied":true,"sourceFilename":"images/icon-check.svg","size":153},"chunkNames":[],"chunkIdHints":[],"auxiliaryChunkNames":[],"auxiliaryChunkIdHints":[],"related":{},"chunks":[],"auxiliaryChunks":[],"isOverSizeLimit":false}],"chunks":[{"rendered":true,"initial":true,"entry":true,"recorded":false,"size":5095,"sizes":{"javascript":1034,"css/mini-extract":4061},"names":["main"],"idHints":[],"runtime":["main"],"files":["assets/main.f8a10ad495058f9c62a8.css","main5a95294ea625ccfbcba9.js"],"auxiliaryFiles":["76d3fa7ddce078ad96b5.svg","83c38a48815855ecc2d7.svg","9f6ed14bb3b0084b05a9.svg"],"hash":"3a8d53a3ba7d72b002b7","childrenByOrder":{},"id":179,"siblings":[],"parents":[],"children":[],"modules":[{"type":"module","moduleType":"javascript/auto","layer":null,"size":1034,"sizes":{"javascript":1034},"built":true,"codeGenerated":true,"buildTimeExecuted":false,"cached":false,"identifier":"/home/stefan/Documents/Proyectos/interactive-pricing-component-main/src/index.js","name":"./src/index.js","nameForCondition":"/home/stefan/Documents/Proyectos/interactive-pricing-component-main/src/index.js","index":0,"preOrderIndex":0,"index2":1,"postOrderIndex":1,"cacheable":true,"optional":false,"orphan":false,"dependent":false,"issuer":null,"issuerName":null,"issuerPath":null,"failed":false,"errors":0,"warnings":0,"profile":{"total":99,"resolving":75,"restoring":0,"building":24,"integration":0,"storing":0,"additionalResolving":0,"additionalIntegration":0,"factory":75,"dependencies":0},"id":138,"issuerId":null,"chunks":[179],"assets":[],"reasons":[{"moduleIdentifier":null,"module":null,"moduleName":null,"resolvedModuleIdentifier":null,"resolvedModule":null,"type":"entry","active":true,"explanation":"","userRequest":"./src/index.js","loc":"main","moduleId":null,"resolvedModuleId":null}],"usedExports":[],"providedExports":[],"optimizationBailout":["Statement (VariableDeclaration) with side effects in source code at 3:0-50"],"depth":0},{"type":"module","moduleType":"css/mini-extract","layer":null,"size":4061,"sizes":{"css/mini-extract":4061},"built":true,"codeGenerated":true,"buildTimeExecuted":false,"cached":false,"identifier":"css|/home/stefan/Documents/Proyectos/interactive-pricing-component-main/node_modules/css-loader/dist/cjs.js!/home/stefan/Documents/Proyectos/interactive-pricing-component-main/src/style.css|0","name":"css ./node_modules/css-loader/dist/cjs.js!./src/style.css","nameForCondition":"/home/stefan/Documents/Proyectos/interactive-pricing-component-main/src/style.css","index":1,"preOrderIndex":1,"index2":0,"postOrderIndex":0,"cacheable":true,"optional":false,"orphan":false,"dependent":true,"issuer":"/home/stefan/Documents/Proyectos/interactive-pricing-component-main/node_modules/mini-css-extract-plugin/dist/loader.js!/home/stefan/Documents/Proyectos/interactive-pricing-component-main/node_modules/css-loader/dist/cjs.js!/home/stefan/Documents/Proyectos/interactive-pricing-component-main/src/style.css","issuerName":"./src/style.css","issuerPath":[{"identifier":"/home/stefan/Documents/Proyectos/interactive-pricing-component-main/src/index.js","name":"./src/index.js","profile":{"total":99,"resolving":75,"restoring":0,"building":24,"integration":0,"storing":0,"additionalResolving":0,"additionalIntegration":0,"factory":75,"dependencies":0},"id":138},{"identifier":"/home/stefan/Documents/Proyectos/interactive-pricing-component-main/node_modules/mini-css-extract-plugin/dist/loader.js!/home/stefan/Documents/Proyectos/interactive-pricing-component-main/node_modules/css-loader/dist/cjs.js!/home/stefan/Documents/Proyectos/interactive-pricing-component-main/src/style.css","name":"./src/style.css","profile":{"total":787,"resolving":532,"restoring":0,"building":255,"integration":0,"storing":0,"additionalResolving":0,"additionalIntegration":0,"factory":532,"dependencies":0},"id":null}],"failed":false,"errors":0,"warnings":0,"profile":{"total":1,"resolving":0,"restoring":0,"building":1,"integration":0,"storing":0,"additionalResolving":0,"additionalIntegration":0,"factory":0,"dependencies":0},"id":null,"issuerId":null,"chunks":[179],"assets":["76d3fa7ddce078ad96b5.svg","83c38a48815855ecc2d7.svg","9f6ed14bb3b0084b05a9.svg"],"reasons":[{"moduleIdentifier":"/home/stefan/Documents/Proyectos/interactive-pricing-component-main/node_modules/mini-css-extract-plugin/dist/loader.js!/home/stefan/Documents/Proyectos/interactive-pricing-component-main/node_modules/css-loader/dist/cjs.js!/home/stefan/Documents/Proyectos/interactive-pricing-component-main/src/style.css","module":"./src/style.css","moduleName":"./src/style.css","resolvedModuleIdentifier":"/home/stefan/Documents/Proyectos/interactive-pricing-component-main/node_modules/mini-css-extract-plugin/dist/loader.js!/home/stefan/Documents/Proyectos/interactive-pricing-component-main/node_modules/css-loader/dist/cjs.js!/home/stefan/Documents/Proyectos/interactive-pricing-component-main/src/style.css","resolvedModule":"./src/style.css","type":"unknown","active":true,"explanation":"","userRequest":null,"moduleId":null,"resolvedModuleId":null}],"usedExports":null,"providedExports":null,"optimizationBailout":["ModuleConcatenation bailout: Module Concatenation is not implemented for CssModule"],"depth":2}],"origins":[{"module":"","moduleIdentifier":"","moduleName":"","loc":"main","request":"./src/index.js"}]}],"modules":[{"type":"module","moduleType":"javascript/auto","layer":null,"size":1034,"sizes":{"javascript":1034},"built":true,"codeGenerated":true,"buildTimeExecuted":false,"cached":false,"identifier":"/home/stefan/Documents/Proyectos/interactive-pricing-component-main/src/index.js","name":"./src/index.js","nameForCondition":"/home/stefan/Documents/Proyectos/interactive-pricing-component-main/src/index.js","index":0,"preOrderIndex":0,"index2":1,"postOrderIndex":1,"cacheable":true,"optional":false,"orphan":false,"issuer":null,"issuerName":null,"issuerPath":null,"failed":false,"errors":0,"warnings":0,"profile":{"total":99,"resolving":75,"restoring":0,"building":24,"integration":0,"storing":0,"additionalResolving":0,"additionalIntegration":0,"factory":75,"dependencies":0},"id":138,"issuerId":null,"chunks":[179],"assets":[],"reasons":[{"moduleIdentifier":null,"module":null,"moduleName":null,"resolvedModuleIdentifier":null,"resolvedModule":null,"type":"entry","active":true,"explanation":"","userRequest":"./src/index.js","loc":"main","moduleId":null,"resolvedModuleId":null}],"usedExports":[],"providedExports":[],"optimizationBailout":["Statement (VariableDeclaration) with side effects in source code at 3:0-50"],"depth":0},{"type":"module","moduleType":"javascript/auto","layer":null,"size":50,"sizes":{"javascript":50},"built":true,"codeGenerated":false,"buildTimeExecuted":false,"cached":false,"identifier":"/home/stefan/Documents/Proyectos/interactive-pricing-component-main/node_modules/mini-css-extract-plugin/dist/loader.js!/home/stefan/Documents/Proyectos/interactive-pricing-component-main/node_modules/css-loader/dist/cjs.js!/home/stefan/Documents/Proyectos/interactive-pricing-component-main/src/style.css","name":"./src/style.css","nameForCondition":"/home/stefan/Documents/Proyectos/interactive-pricing-component-main/src/style.css","index":null,"preOrderIndex":null,"index2":null,"postOrderIndex":null,"cacheable":true,"optional":false,"orphan":true,"issuer":"/home/stefan/Documents/Proyectos/interactive-pricing-component-main/src/index.js","issuerName":"./src/index.js","issuerPath":[{"identifier":"/home/stefan/Documents/Proyectos/interactive-pricing-component-main/src/index.js","name":"./src/index.js","profile":{"total":99,"resolving":75,"restoring":0,"building":24,"integration":0,"storing":0,"additionalResolving":0,"additionalIntegration":0,"factory":75,"dependencies":0},"id":138}],"failed":false,"errors":0,"warnings":0,"profile":{"total":787,"resolving":532,"restoring":0,"building":255,"integration":0,"storing":0,"additionalResolving":0,"additionalIntegration":0,"factory":532,"dependencies":0},"id":null,"issuerId":138,"chunks":[],"assets":[],"reasons":[{"moduleIdentifier":"/home/stefan/Documents/Proyectos/interactive-pricing-component-main/src/index.js","module":"./src/index.js","moduleName":"./src/index.js","resolvedModuleIdentifier":"/home/stefan/Documents/Proyectos/interactive-pricing-component-main/src/index.js","resolvedModule":"./src/index.js","type":"harmony side effect evaluation","active":true,"explanation":"","userRequest":"./style.css","loc":"1:0-20","moduleId":138,"resolvedModuleId":138}],"usedExports":false,"providedExports":[],"optimizationBailout":["ModuleConcatenation bailout: Module is not in any chunk"],"depth":1},{"type":"module","moduleType":"css/mini-extract","layer":null,"size":4061,"sizes":{"css/mini-extract":4061},"built":true,"codeGenerated":true,"buildTimeExecuted":false,"cached":false,"identifier":"css|/home/stefan/Documents/Proyectos/interactive-pricing-component-main/node_modules/css-loader/dist/cjs.js!/home/stefan/Documents/Proyectos/interactive-pricing-component-main/src/style.css|0","name":"css ./node_modules/css-loader/dist/cjs.js!./src/style.css","nameForCondition":"/home/stefan/Documents/Proyectos/interactive-pricing-component-main/src/style.css","index":1,"preOrderIndex":1,"index2":0,"postOrderIndex":0,"cacheable":true,"optional":false,"orphan":false,"issuer":"/home/stefan/Documents/Proyectos/interactive-pricing-component-main/node_modules/mini-css-extract-plugin/dist/loader.js!/home/stefan/Documents/Proyectos/interactive-pricing-component-main/node_modules/css-loader/dist/cjs.js!/home/stefan/Documents/Proyectos/interactive-pricing-component-main/src/style.css","issuerName":"./src/style.css","issuerPath":[{"identifier":"/home/stefan/Documents/Proyectos/interactive-pricing-component-main/src/index.js","name":"./src/index.js","profile":{"total":99,"resolving":75,"restoring":0,"building":24,"integration":0,"storing":0,"additionalResolving":0,"additionalIntegration":0,"factory":75,"dependencies":0},"id":138},{"identifier":"/home/stefan/Documents/Proyectos/interactive-pricing-component-main/node_modules/mini-css-extract-plugin/dist/loader.js!/home/stefan/Documents/Proyectos/interactive-pricing-component-main/node_modules/css-loader/dist/cjs.js!/home/stefan/Documents/Proyectos/interactive-pricing-component-main/src/style.css","name":"./src/style.css","profile":{"total":787,"resolving":532,"restoring":0,"building":255,"integration":0,"storing":0,"additionalResolving":0,"additionalIntegration":0,"factory":532,"dependencies":0},"id":null}],"failed":false,"errors":0,"warnings":0,"profile":{"total":1,"resolving":0,"restoring":0,"building":1,"integration":0,"storing":0,"additionalResolving":0,"additionalIntegration":0,"factory":0,"dependencies":0},"id":null,"issuerId":null,"chunks":[179],"assets":["76d3fa7ddce078ad96b5.svg","83c38a48815855ecc2d7.svg","9f6ed14bb3b0084b05a9.svg"],"reasons":[{"moduleIdentifier":"/home/stefan/Documents/Proyectos/interactive-pricing-component-main/node_modules/mini-css-extract-plugin/dist/loader.js!/home/stefan/Documents/Proyectos/interactive-pricing-component-main/node_modules/css-loader/dist/cjs.js!/home/stefan/Documents/Proyectos/interactive-pricing-component-main/src/style.css","module":"./src/style.css","moduleName":"./src/style.css","resolvedModuleIdentifier":"/home/stefan/Documents/Proyectos/interactive-pricing-component-main/node_modules/mini-css-extract-plugin/dist/loader.js!/home/stefan/Documents/Proyectos/interactive-pricing-component-main/node_modules/css-loader/dist/cjs.js!/home/stefan/Documents/Proyectos/interactive-pricing-component-main/src/style.css","resolvedModule":"./src/style.css","type":"unknown","active":true,"explanation":"","userRequest":null,"moduleId":null,"resolvedModuleId":null}],"usedExports":null,"providedExports":null,"optimizationBailout":["ModuleConcatenation bailout: Module Concatenation is not implemented for CssModule"],"depth":2}],"entrypoints":{"main":{"name":"main","chunks":[179],"assets":[{"name":"assets/main.f8a10ad495058f9c62a8.css","size":3007},{"name":"main5a95294ea625ccfbcba9.js","size":654}],"filteredAssets":0,"assetsSize":3661,"auxiliaryAssets":[{"name":"76d3fa7ddce078ad96b5.svg","size":170},{"name":"83c38a48815855ecc2d7.svg","size":153},{"name":"9f6ed14bb3b0084b05a9.svg","size":196}],"filteredAuxiliaryAssets":0,"auxiliaryAssetsSize":519,"children":{},"childAssets":{},"isOverSizeLimit":false}},"namedChunkGroups":{"main":{"name":"main","chunks":[179],"assets":[{"name":"assets/main.f8a10ad495058f9c62a8.css","size":3007},{"name":"main5a95294ea625ccfbcba9.js","size":654}],"filteredAssets":0,"assetsSize":3661,"auxiliaryAssets":[{"name":"76d3fa7ddce078ad96b5.svg","size":170},{"name":"83c38a48815855ecc2d7.svg","size":153},{"name":"9f6ed14bb3b0084b05a9.svg","size":196}],"filteredAuxiliaryAssets":0,"auxiliaryAssetsSize":519,"children":{},"childAssets":{},"isOverSizeLimit":false}},"errors":[],"errorsCount":0,"warnings":[{"message":"configuration\nThe 'mode' option has not been set, webpack will fallback to 'production' for this value.\nSet 'mode' option to 'development' or 'production' to enable defaults for each environment.\nYou can also set it to 'none' to disable any default behavior. Learn more: https://webpack.js.org/configuration/mode/","stack":"NoModeWarning: configuration\nThe 'mode' option has not been set, webpack will fallback to 'production' for this value.\nSet 'mode' option to 'development' or 'production' to enable defaults for each environment.\nYou can also set it to 'none' to disable any default behavior. Learn more: https://webpack.js.org/configuration/mode/\n    at /home/stefan/Documents/Proyectos/interactive-pricing-component-main/node_modules/webpack/lib/WarnNoModeSetPlugin.js:20:30\n    at Hook.eval [as call] (eval at create (/home/stefan/Documents/Proyectos/interactive-pricing-component-main/node_modules/tapable/lib/HookCodeFactory.js:19:10), <anonymous>:25:1)\n    at Hook.CALL_DELEGATE [as _call] (/home/stefan/Documents/Proyectos/interactive-pricing-component-main/node_modules/tapable/lib/Hook.js:14:14)\n    at Compiler.newCompilation (/home/stefan/Documents/Proyectos/interactive-pricing-component-main/node_modules/webpack/lib/Compiler.js:1043:30)\n    at /home/stefan/Documents/Proyectos/interactive-pricing-component-main/node_modules/webpack/lib/Compiler.js:1088:29\n    at Hook.eval [as callAsync] (eval at create (/home/stefan/Documents/Proyectos/interactive-pricing-component-main/node_modules/tapable/lib/HookCodeFactory.js:33:10), <anonymous>:6:1)\n    at Hook.CALL_ASYNC_DELEGATE [as _callAsync] (/home/stefan/Documents/Proyectos/interactive-pricing-component-main/node_modules/tapable/lib/Hook.js:18:14)\n    at Compiler.compile (/home/stefan/Documents/Proyectos/interactive-pricing-component-main/node_modules/webpack/lib/Compiler.js:1083:28)\n    at /home/stefan/Documents/Proyectos/interactive-pricing-component-main/node_modules/webpack/lib/Compiler.js:508:12\n    at Compiler.readRecords (/home/stefan/Documents/Proyectos/interactive-pricing-component-main/node_modules/webpack/lib/Compiler.js:920:11)"}],"warningsCount":1,"children":[{"name":"HtmlWebpackCompiler","hash":"9cd1951adbdf02132a8b","version":"5.50.0","time":624,"builtAt":1629309709477,"publicPath":"","outputPath":"/home/stefan/Documents/Proyectos/interactive-pricing-component-main/dist","assetsByChunkName":{},"assets":[],"chunks":[{"rendered":true,"initial":true,"entry":true,"recorded":false,"size":2889,"sizes":{"javascript":2449,"runtime":440},"names":["HtmlWebpackPlugin_0-0"],"idHints":[],"runtime":["HtmlWebpackPlugin_0-0"],"files":[],"auxiliaryFiles":[],"hash":"59442b516c4baf860325","childrenByOrder":{},"id":563,"siblings":[],"parents":[],"children":[],"modules":[{"type":"module","moduleType":"javascript/auto","layer":null,"size":2372,"sizes":{"javascript":2372},"built":true,"codeGenerated":true,"buildTimeExecuted":false,"cached":false,"identifier":"/home/stefan/Documents/Proyectos/interactive-pricing-component-main/node_modules/html-webpack-plugin/lib/loader.js!/home/stefan/Documents/Proyectos/interactive-pricing-component-main/public/index.html","name":"./node_modules/html-webpack-plugin/lib/loader.js!./public/index.html","nameForCondition":"/home/stefan/Documents/Proyectos/interactive-pricing-component-main/public/index.html","index":1,"preOrderIndex":1,"index2":1,"postOrderIndex":1,"cacheable":true,"optional":false,"orphan":false,"dependent":false,"issuer":null,"issuerName":null,"issuerPath":null,"failed":false,"errors":0,"warnings":0,"profile":{"total":0,"resolving":0,"restoring":0,"building":0,"integration":0,"storing":0,"additionalResolving":0,"additionalIntegration":0,"factory":0,"dependencies":0},"id":759,"issuerId":null,"chunks":[563],"assets":[],"reasons":[{"moduleIdentifier":"/home/stefan/Documents/Proyectos/interactive-pricing-component-main/node_modules/html-webpack-plugin/lib/loader.js!/home/stefan/Documents/Proyectos/interactive-pricing-component-main/public/index.html","module":"./node_modules/html-webpack-plugin/lib/loader.js!./public/index.html","moduleName":"./node_modules/html-webpack-plugin/lib/loader.js!./public/index.html","resolvedModuleIdentifier":"/home/stefan/Documents/Proyectos/interactive-pricing-component-main/node_modules/html-webpack-plugin/lib/loader.js!/home/stefan/Documents/Proyectos/interactive-pricing-component-main/public/index.html","resolvedModule":"./node_modules/html-webpack-plugin/lib/loader.js!./public/index.html","type":"cjs self exports reference","active":true,"explanation":"","userRequest":null,"loc":"1:133-147","moduleId":759,"resolvedModuleId":759},{"moduleIdentifier":null,"module":null,"moduleName":null,"resolvedModuleIdentifier":null,"resolvedModule":null,"type":"entry","active":true,"explanation":"","userRequest":"/home/stefan/Documents/Proyectos/interactive-pricing-component-main/node_modules/html-webpack-plugin/lib/loader.js!/home/stefan/Documents/Proyectos/interactive-pricing-component-main/public/index.html","loc":"HtmlWebpackPlugin_0-0","moduleId":null,"resolvedModuleId":null},{"moduleIdentifier":null,"module":null,"moduleName":null,"resolvedModuleIdentifier":null,"resolvedModule":null,"type":null,"active":true,"explanation":"used as library export","userRequest":null,"moduleId":null,"resolvedModuleId":null}],"usedExports":null,"providedExports":null,"optimizationBailout":["CommonJS bailout: module.exports is used directly at 1:133-147","Statement (VariableDeclaration) with side effects in source code at 1:0-133","ModuleConcatenation bailout: Module is not an ECMAScript module"],"depth":0},{"type":"module","moduleType":"javascript/esm","layer":null,"size":77,"sizes":{"javascript":77},"built":true,"codeGenerated":true,"buildTimeExecuted":false,"cached":false,"identifier":"javascript/esm|data:text/javascript,__webpack_public_path__ = __webpack_base_uri__ = htmlWebpackPluginPublicPath;","name":"data:text/javascript,__webpack_public_path__ = __webpack_base_uri__ = htmlWebpackPluginPublicPath;","nameForCondition":"data:text/javascript,__webpack_public_path__ = __webpack_base_uri__ = htmlWebpackPluginPublicPath;","index":0,"preOrderIndex":0,"index2":0,"postOrderIndex":0,"cacheable":true,"optional":false,"orphan":false,"dependent":false,"issuer":null,"issuerName":null,"issuerPath":null,"failed":false,"errors":0,"warnings":0,"profile":{"total":34,"resolving":13,"restoring":0,"building":21,"integration":0,"storing":0,"additionalResolving":0,"additionalIntegration":0,"factory":13,"dependencies":0},"id":163,"issuerId":null,"chunks":[563],"assets":[],"reasons":[{"moduleIdentifier":null,"module":null,"moduleName":null,"resolvedModuleIdentifier":null,"resolvedModule":null,"type":"entry","active":true,"explanation":"","userRequest":"data:text/javascript,__webpack_public_path__ = __webpack_base_uri__ = htmlWebpackPluginPublicPath;","loc":"HtmlWebpackPlugin_0-0","moduleId":null,"resolvedModuleId":null}],"usedExports":[],"providedExports":[],"optimizationBailout":["Statement (ExpressionStatement) with side effects in source code at 1:0-77"],"depth":0},{"type":"module","moduleType":"runtime","layer":null,"size":88,"sizes":{"runtime":88},"built":false,"codeGenerated":true,"buildTimeExecuted":false,"cached":false,"identifier":"webpack/runtime/hasOwnProperty shorthand","name":"webpack/runtime/hasOwnProperty shorthand","nameForCondition":null,"index":null,"preOrderIndex":null,"index2":null,"postOrderIndex":null,"optional":false,"orphan":false,"dependent":false,"failed":false,"errors":0,"warnings":0,"id":"","chunks":[563],"assets":[],"reasons":[],"usedExports":null,"providedExports":[],"optimizationBailout":[],"depth":null},{"type":"module","moduleType":"runtime","layer":null,"size":27,"sizes":{"runtime":27},"built":false,"codeGenerated":true,"buildTimeExecuted":false,"cached":false,"identifier":"webpack/runtime/publicPath","name":"webpack/runtime/publicPath","nameForCondition":null,"index":null,"preOrderIndex":null,"index2":null,"postOrderIndex":null,"optional":false,"orphan":false,"dependent":false,"failed":false,"errors":0,"warnings":0,"id":"","chunks":[563],"assets":[],"reasons":[],"usedExports":null,"providedExports":[],"optimizationBailout":[],"depth":null},{"type":"module","moduleType":"runtime","layer":null,"size":325,"sizes":{"runtime":325},"built":false,"codeGenerated":true,"buildTimeExecuted":false,"cached":false,"identifier":"webpack/runtime/require chunk loading","name":"webpack/runtime/require chunk loading","nameForCondition":null,"index":null,"preOrderIndex":null,"index2":null,"postOrderIndex":null,"optional":false,"orphan":false,"dependent":false,"failed":false,"errors":0,"warnings":0,"id":"","chunks":[563],"assets":[],"reasons":[],"usedExports":null,"providedExports":[],"optimizationBailout":[],"depth":null}],"origins":[{"module":"","moduleIdentifier":"","moduleName":"","loc":"HtmlWebpackPlugin_0-0","request":"/home/stefan/Documents/Proyectos/interactive-pricing-component-main/node_modules/html-webpack-plugin/lib/loader.js!/home/stefan/Documents/Proyectos/interactive-pricing-component-main/public/index.html"},{"module":"","moduleIdentifier":"","moduleName":"","loc":"HtmlWebpackPlugin_0-0","request":"data:text/javascript,__webpack_public_path__ = __webpack_base_uri__ = htmlWebpackPluginPublicPath;"}]}],"modules":[{"type":"module","moduleType":"javascript/esm","layer":null,"size":77,"sizes":{"javascript":77},"built":true,"codeGenerated":true,"buildTimeExecuted":false,"cached":false,"identifier":"javascript/esm|data:text/javascript,__webpack_public_path__ = __webpack_base_uri__ = htmlWebpackPluginPublicPath;","name":"data:text/javascript,__webpack_public_path__ = __webpack_base_uri__ = htmlWebpackPluginPublicPath;","nameForCondition":"data:text/javascript,__webpack_public_path__ = __webpack_base_uri__ = htmlWebpackPluginPublicPath;","index":0,"preOrderIndex":0,"index2":0,"postOrderIndex":0,"cacheable":true,"optional":false,"orphan":false,"issuer":null,"issuerName":null,"issuerPath":null,"failed":false,"errors":0,"warnings":0,"profile":{"total":34,"resolving":13,"restoring":0,"building":21,"integration":0,"storing":0,"additionalResolving":0,"additionalIntegration":0,"factory":13,"dependencies":0},"id":163,"issuerId":null,"chunks":[563],"assets":[],"reasons":[{"moduleIdentifier":null,"module":null,"moduleName":null,"resolvedModuleIdentifier":null,"resolvedModule":null,"type":"entry","active":true,"explanation":"","userRequest":"data:text/javascript,__webpack_public_path__ = __webpack_base_uri__ = htmlWebpackPluginPublicPath;","loc":"HtmlWebpackPlugin_0-0","moduleId":null,"resolvedModuleId":null}],"usedExports":[],"providedExports":[],"optimizationBailout":["Statement (ExpressionStatement) with side effects in source code at 1:0-77"],"depth":0},{"type":"module","moduleType":"javascript/auto","layer":null,"size":2372,"sizes":{"javascript":2372},"built":true,"codeGenerated":true,"buildTimeExecuted":false,"cached":false,"identifier":"/home/stefan/Documents/Proyectos/interactive-pricing-component-main/node_modules/html-webpack-plugin/lib/loader.js!/home/stefan/Documents/Proyectos/interactive-pricing-component-main/public/index.html","name":"./node_modules/html-webpack-plugin/lib/loader.js!./public/index.html","nameForCondition":"/home/stefan/Documents/Proyectos/interactive-pricing-component-main/public/index.html","index":1,"preOrderIndex":1,"index2":1,"postOrderIndex":1,"cacheable":true,"optional":false,"orphan":false,"issuer":null,"issuerName":null,"issuerPath":null,"failed":false,"errors":0,"warnings":0,"profile":{"total":0,"resolving":0,"restoring":0,"building":0,"integration":0,"storing":0,"additionalResolving":0,"additionalIntegration":0,"factory":0,"dependencies":0},"id":759,"issuerId":null,"chunks":[563],"assets":[],"reasons":[{"moduleIdentifier":"/home/stefan/Documents/Proyectos/interactive-pricing-component-main/node_modules/html-webpack-plugin/lib/loader.js!/home/stefan/Documents/Proyectos/interactive-pricing-component-main/public/index.html","module":"./node_modules/html-webpack-plugin/lib/loader.js!./public/index.html","moduleName":"./node_modules/html-webpack-plugin/lib/loader.js!./public/index.html","resolvedModuleIdentifier":"/home/stefan/Documents/Proyectos/interactive-pricing-component-main/node_modules/html-webpack-plugin/lib/loader.js!/home/stefan/Documents/Proyectos/interactive-pricing-component-main/public/index.html","resolvedModule":"./node_modules/html-webpack-plugin/lib/loader.js!./public/index.html","type":"cjs self exports reference","active":true,"explanation":"","userRequest":null,"loc":"1:133-147","moduleId":759,"resolvedModuleId":759},{"moduleIdentifier":null,"module":null,"moduleName":null,"resolvedModuleIdentifier":null,"resolvedModule":null,"type":"entry","active":true,"explanation":"","userRequest":"/home/stefan/Documents/Proyectos/interactive-pricing-component-main/node_modules/html-webpack-plugin/lib/loader.js!/home/stefan/Documents/Proyectos/interactive-pricing-component-main/public/index.html","loc":"HtmlWebpackPlugin_0-0","moduleId":null,"resolvedModuleId":null},{"moduleIdentifier":null,"module":null,"moduleName":null,"resolvedModuleIdentifier":null,"resolvedModule":null,"type":null,"active":true,"explanation":"used as library export","userRequest":null,"moduleId":null,"resolvedModuleId":null}],"usedExports":null,"providedExports":null,"optimizationBailout":["CommonJS bailout: module.exports is used directly at 1:133-147","Statement (VariableDeclaration) with side effects in source code at 1:0-133","ModuleConcatenation bailout: Module is not an ECMAScript module"],"depth":0},{"type":"module","moduleType":"runtime","layer":null,"size":88,"sizes":{"runtime":88},"built":false,"codeGenerated":true,"buildTimeExecuted":false,"cached":false,"identifier":"webpack/runtime/hasOwnProperty shorthand","name":"webpack/runtime/hasOwnProperty shorthand","nameForCondition":null,"index":null,"preOrderIndex":null,"index2":null,"postOrderIndex":null,"optional":false,"orphan":false,"failed":false,"errors":0,"warnings":0,"id":"","chunks":[563],"assets":[],"reasons":[],"usedExports":null,"providedExports":[],"optimizationBailout":[],"depth":null},{"type":"module","moduleType":"runtime","layer":null,"size":27,"sizes":{"runtime":27},"built":false,"codeGenerated":true,"buildTimeExecuted":false,"cached":false,"identifier":"webpack/runtime/publicPath","name":"webpack/runtime/publicPath","nameForCondition":null,"index":null,"preOrderIndex":null,"index2":null,"postOrderIndex":null,"optional":false,"orphan":false,"failed":false,"errors":0,"warnings":0,"id":"","chunks":[563],"assets":[],"reasons":[],"usedExports":null,"providedExports":[],"optimizationBailout":[],"depth":null},{"type":"module","moduleType":"runtime","layer":null,"size":325,"sizes":{"runtime":325},"built":false,"codeGenerated":true,"buildTimeExecuted":false,"cached":false,"identifier":"webpack/runtime/require chunk loading","name":"webpack/runtime/require chunk loading","nameForCondition":null,"index":null,"preOrderIndex":null,"index2":null,"postOrderIndex":null,"optional":false,"orphan":false,"failed":false,"errors":0,"warnings":0,"id":"","chunks":[563],"assets":[],"reasons":[],"usedExports":null,"providedExports":[],"optimizationBailout":[],"depth":null}],"entrypoints":{"HtmlWebpackPlugin_0-0":{"name":"HtmlWebpackPlugin_0-0","chunks":[563],"assets":[],"filteredAssets":0,"assetsSize":0,"auxiliaryAssets":[],"filteredAuxiliaryAssets":0,"auxiliaryAssetsSize":0,"children":{},"childAssets":{},"isOverSizeLimit":false}},"namedChunkGroups":{"HtmlWebpackPlugin_0-0":{"name":"HtmlWebpackPlugin_0-0","chunks":[563],"assets":[],"filteredAssets":0,"assetsSize":0,"auxiliaryAssets":[],"filteredAuxiliaryAssets":0,"auxiliaryAssetsSize":0,"children":{},"childAssets":{},"isOverSizeLimit":false}},"errors":[],"errorsCount":0,"warnings":[],"warningsCount":0,"children":[]},{"name":"mini-css-extract-plugin /home/stefan/Documents/Proyectos/interactive-pricing-component-main/node_modules/css-loader/dist/cjs.js!/home/stefan/Documents/Proyectos/interactive-pricing-component-main/src/style.css","hash":"f6400de5d1674d832ce9","version":"5.50.0","time":235,"builtAt":1629309709743,"publicPath":"__MINI_CSS_EXTRACT_PLUGIN_PUBLIC_PATH__","outputPath":"/home/stefan/Documents/Proyectos/interactive-pricing-component-main/dist","assetsByChunkName":{},"assets":[{"type":"asset","name":"9f6ed14bb3b0084b05a9.svg","size":196,"emitted":false,"comparedForEmit":false,"cached":true,"info":{"sourceFilename":"images/pattern-circles.svg","immutable":true,"contenthash":"9f6ed14bb3b0084b05a9"},"chunkNames":[],"chunkIdHints":[],"auxiliaryChunkNames":["child"],"auxiliaryChunkIdHints":[],"related":{},"chunks":[],"auxiliaryChunks":[396],"isOverSizeLimit":false},{"type":"asset","name":"76d3fa7ddce078ad96b5.svg","size":170,"emitted":false,"comparedForEmit":false,"cached":true,"info":{"sourceFilename":"images/bg-pattern.svg","immutable":true,"contenthash":"76d3fa7ddce078ad96b5"},"chunkNames":[],"chunkIdHints":[],"auxiliaryChunkNames":["child"],"auxiliaryChunkIdHints":[],"related":{},"chunks":[],"auxiliaryChunks":[396],"isOverSizeLimit":false},{"type":"asset","name":"83c38a48815855ecc2d7.svg","size":153,"emitted":false,"comparedForEmit":false,"cached":true,"info":{"sourceFilename":"images/icon-check.svg","immutable":true,"contenthash":"83c38a48815855ecc2d7"},"chunkNames":[],"chunkIdHints":[],"auxiliaryChunkNames":["child"],"auxiliaryChunkIdHints":[],"related":{},"chunks":[],"auxiliaryChunks":[396],"isOverSizeLimit":false}],"chunks":[{"rendered":true,"initial":true,"entry":true,"recorded":false,"size":9783,"sizes":{"javascript":7761,"asset":519,"runtime":1503},"names":["child"],"idHints":[],"runtime":["child"],"files":[],"auxiliaryFiles":["76d3fa7ddce078ad96b5.svg","83c38a48815855ecc2d7.svg","9f6ed14bb3b0084b05a9.svg"],"hash":"419dab089acd5263ac3e","childrenByOrder":{},"id":396,"siblings":[],"parents":[],"children":[],"modules":[{"type":"module","moduleType":"asset/resource","layer":null,"size":42,"sizes":{"javascript":42,"asset":170},"built":true,"codeGenerated":true,"buildTimeExecuted":false,"cached":false,"identifier":"asset/resource|/home/stefan/Documents/Proyectos/interactive-pricing-component-main/images/bg-pattern.svg","name":"./images/bg-pattern.svg","nameForCondition":"/home/stefan/Documents/Proyectos/interactive-pricing-component-main/images/bg-pattern.svg","index":3,"preOrderIndex":3,"index2":2,"postOrderIndex":2,"cacheable":true,"optional":false,"orphan":false,"dependent":true,"issuer":"/home/stefan/Documents/Proyectos/interactive-pricing-component-main/node_modules/css-loader/dist/cjs.js!/home/stefan/Documents/Proyectos/interactive-pricing-component-main/src/style.css","issuerName":"./node_modules/css-loader/dist/cjs.js!./src/style.css","issuerPath":[{"identifier":"/home/stefan/Documents/Proyectos/interactive-pricing-component-main/node_modules/css-loader/dist/cjs.js!/home/stefan/Documents/Proyectos/interactive-pricing-component-main/src/style.css","name":"./node_modules/css-loader/dist/cjs.js!./src/style.css","profile":{"total":157,"resolving":7,"restoring":0,"building":150,"integration":0,"storing":0,"additionalResolving":0,"additionalIntegration":0,"factory":7,"dependencies":0},"id":426}],"failed":false,"errors":0,"warnings":0,"profile":{"total":37,"resolving":19,"restoring":0,"building":18,"integration":0,"storing":0,"additionalResolving":0,"additionalIntegration":0,"factory":19,"dependencies":0},"id":576,"issuerId":426,"chunks":[396],"assets":[],"reasons":[{"moduleIdentifier":"/home/stefan/Documents/Proyectos/interactive-pricing-component-main/node_modules/css-loader/dist/cjs.js!/home/stefan/Documents/Proyectos/interactive-pricing-component-main/src/style.css","module":"./node_modules/css-loader/dist/cjs.js!./src/style.css","moduleName":"./node_modules/css-loader/dist/cjs.js!./src/style.css","resolvedModuleIdentifier":"/home/stefan/Documents/Proyectos/interactive-pricing-component-main/node_modules/css-loader/dist/cjs.js!/home/stefan/Documents/Proyectos/interactive-pricing-component-main/src/style.css","resolvedModule":"./node_modules/css-loader/dist/cjs.js!./src/style.css","type":"new URL()","active":true,"explanation":"","userRequest":"../images/bg-pattern.svg","loc":"4:36-88","moduleId":426,"resolvedModuleId":426}],"usedExports":true,"providedExports":[],"optimizationBailout":["ModuleConcatenation bailout: Module Concatenation is not implemented for AssetGenerator"],"depth":1},{"type":"module","moduleType":"asset/resource","layer":null,"size":42,"sizes":{"javascript":42,"asset":153},"built":true,"codeGenerated":true,"buildTimeExecuted":false,"cached":false,"identifier":"asset/resource|/home/stefan/Documents/Proyectos/interactive-pricing-component-main/images/icon-check.svg","name":"./images/icon-check.svg","nameForCondition":"/home/stefan/Documents/Proyectos/interactive-pricing-component-main/images/icon-check.svg","index":5,"preOrderIndex":5,"index2":4,"postOrderIndex":4,"cacheable":true,"optional":false,"orphan":false,"dependent":true,"issuer":"/home/stefan/Documents/Proyectos/interactive-pricing-component-main/node_modules/css-loader/dist/cjs.js!/home/stefan/Documents/Proyectos/interactive-pricing-component-main/src/style.css","issuerName":"./node_modules/css-loader/dist/cjs.js!./src/style.css","issuerPath":[{"identifier":"/home/stefan/Documents/Proyectos/interactive-pricing-component-main/node_modules/css-loader/dist/cjs.js!/home/stefan/Documents/Proyectos/interactive-pricing-component-main/src/style.css","name":"./node_modules/css-loader/dist/cjs.js!./src/style.css","profile":{"total":157,"resolving":7,"restoring":0,"building":150,"integration":0,"storing":0,"additionalResolving":0,"additionalIntegration":0,"factory":7,"dependencies":0},"id":426}],"failed":false,"errors":0,"warnings":0,"profile":{"total":38,"resolving":19,"restoring":0,"building":19,"integration":0,"storing":0,"additionalResolving":0,"additionalIntegration":0,"factory":19,"dependencies":0},"id":328,"issuerId":426,"chunks":[396],"assets":[],"reasons":[{"moduleIdentifier":"/home/stefan/Documents/Proyectos/interactive-pricing-component-main/node_modules/css-loader/dist/cjs.js!/home/stefan/Documents/Proyectos/interactive-pricing-component-main/src/style.css","module":"./node_modules/css-loader/dist/cjs.js!./src/style.css","moduleName":"./node_modules/css-loader/dist/cjs.js!./src/style.css","resolvedModuleIdentifier":"/home/stefan/Documents/Proyectos/interactive-pricing-component-main/node_modules/css-loader/dist/cjs.js!/home/stefan/Documents/Proyectos/interactive-pricing-component-main/src/style.css","resolvedModule":"./node_modules/css-loader/dist/cjs.js!./src/style.css","type":"new URL()","active":true,"explanation":"","userRequest":"../images/icon-check.svg","loc":"6:36-88","moduleId":426,"resolvedModuleId":426}],"usedExports":true,"providedExports":[],"optimizationBailout":["ModuleConcatenation bailout: Module Concatenation is not implemented for AssetGenerator"],"depth":1},{"type":"module","moduleType":"asset/resource","layer":null,"size":42,"sizes":{"javascript":42,"asset":196},"built":true,"codeGenerated":true,"buildTimeExecuted":false,"cached":false,"identifier":"asset/resource|/home/stefan/Documents/Proyectos/interactive-pricing-component-main/images/pattern-circles.svg","name":"./images/pattern-circles.svg","nameForCondition":"/home/stefan/Documents/Proyectos/interactive-pricing-component-main/images/pattern-circles.svg","index":4,"preOrderIndex":4,"index2":3,"postOrderIndex":3,"cacheable":true,"optional":false,"orphan":false,"dependent":true,"issuer":"/home/stefan/Documents/Proyectos/interactive-pricing-component-main/node_modules/css-loader/dist/cjs.js!/home/stefan/Documents/Proyectos/interactive-pricing-component-main/src/style.css","issuerName":"./node_modules/css-loader/dist/cjs.js!./src/style.css","issuerPath":[{"identifier":"/home/stefan/Documents/Proyectos/interactive-pricing-component-main/node_modules/css-loader/dist/cjs.js!/home/stefan/Documents/Proyectos/interactive-pricing-component-main/src/style.css","name":"./node_modules/css-loader/dist/cjs.js!./src/style.css","profile":{"total":157,"resolving":7,"restoring":0,"building":150,"integration":0,"storing":0,"additionalResolving":0,"additionalIntegration":0,"factory":7,"dependencies":0},"id":426}],"failed":false,"errors":0,"warnings":0,"profile":{"total":37,"resolving":19,"restoring":0,"building":18,"integration":0,"storing":0,"additionalResolving":0,"additionalIntegration":0,"factory":19,"dependencies":0},"id":175,"issuerId":426,"chunks":[396],"assets":[],"reasons":[{"moduleIdentifier":"/home/stefan/Documents/Proyectos/interactive-pricing-component-main/node_modules/css-loader/dist/cjs.js!/home/stefan/Documents/Proyectos/interactive-pricing-component-main/src/style.css","module":"./node_modules/css-loader/dist/cjs.js!./src/style.css","moduleName":"./node_modules/css-loader/dist/cjs.js!./src/style.css","resolvedModuleIdentifier":"/home/stefan/Documents/Proyectos/interactive-pricing-component-main/node_modules/css-loader/dist/cjs.js!/home/stefan/Documents/Proyectos/interactive-pricing-component-main/src/style.css","resolvedModule":"./node_modules/css-loader/dist/cjs.js!./src/style.css","type":"new URL()","active":true,"explanation":"","userRequest":"../images/pattern-circles.svg","loc":"5:36-93","moduleId":426,"resolvedModuleId":426}],"usedExports":true,"providedExports":[],"optimizationBailout":["ModuleConcatenation bailout: Module Concatenation is not implemented for AssetGenerator"],"depth":1},{"type":"module","moduleType":"javascript/auto","layer":null,"size":5213,"sizes":{"javascript":5213},"built":true,"codeGenerated":true,"buildTimeExecuted":false,"cached":false,"identifier":"/home/stefan/Documents/Proyectos/interactive-pricing-component-main/node_modules/css-loader/dist/cjs.js!/home/stefan/Documents/Proyectos/interactive-pricing-component-main/src/style.css","name":"./node_modules/css-loader/dist/cjs.js!./src/style.css","nameForCondition":"/home/stefan/Documents/Proyectos/interactive-pricing-component-main/src/style.css","index":0,"preOrderIndex":0,"index2":5,"postOrderIndex":5,"cacheable":true,"optional":false,"orphan":false,"dependent":false,"issuer":null,"issuerName":null,"issuerPath":null,"failed":false,"errors":0,"warnings":0,"profile":{"total":157,"resolving":7,"restoring":0,"building":150,"integration":0,"storing":0,"additionalResolving":0,"additionalIntegration":0,"factory":7,"dependencies":0},"id":426,"issuerId":null,"chunks":[396],"assets":[],"reasons":[{"moduleIdentifier":null,"module":null,"moduleName":null,"resolvedModuleIdentifier":null,"resolvedModule":null,"type":"entry","active":true,"explanation":"","userRequest":"!!/home/stefan/Documents/Proyectos/interactive-pricing-component-main/node_modules/css-loader/dist/cjs.js!/home/stefan/Documents/Proyectos/interactive-pricing-component-main/src/style.css","loc":"child","moduleId":null,"resolvedModuleId":null},{"moduleIdentifier":null,"module":null,"moduleName":null,"resolvedModuleIdentifier":null,"resolvedModule":null,"type":null,"active":true,"explanation":"used as library export","userRequest":null,"moduleId":null,"resolvedModuleId":null}],"usedExports":true,"providedExports":["default"],"optimizationBailout":["Statement (VariableDeclaration) with side effects in source code at 7:0-84","ModuleConcatenation bailout: Module uses module.id"],"depth":0},{"type":"module","moduleType":"javascript/auto","layer":null,"size":1605,"sizes":{"javascript":1605},"built":true,"codeGenerated":true,"buildTimeExecuted":false,"cached":false,"identifier":"/home/stefan/Documents/Proyectos/interactive-pricing-component-main/node_modules/css-loader/dist/runtime/api.js","name":"./node_modules/css-loader/dist/runtime/api.js","nameForCondition":"/home/stefan/Documents/Proyectos/interactive-pricing-component-main/node_modules/css-loader/dist/runtime/api.js","index":1,"preOrderIndex":1,"index2":0,"postOrderIndex":0,"cacheable":true,"optional":false,"orphan":false,"dependent":true,"issuer":"/home/stefan/Documents/Proyectos/interactive-pricing-component-main/node_modules/css-loader/dist/cjs.js!/home/stefan/Documents/Proyectos/interactive-pricing-component-main/src/style.css","issuerName":"./node_modules/css-loader/dist/cjs.js!./src/style.css","issuerPath":[{"identifier":"/home/stefan/Documents/Proyectos/interactive-pricing-component-main/node_modules/css-loader/dist/cjs.js!/home/stefan/Documents/Proyectos/interactive-pricing-component-main/src/style.css","name":"./node_modules/css-loader/dist/cjs.js!./src/style.css","profile":{"total":157,"resolving":7,"restoring":0,"building":150,"integration":0,"storing":0,"additionalResolving":0,"additionalIntegration":0,"factory":7,"dependencies":0},"id":426}],"failed":false,"errors":0,"warnings":0,"profile":{"total":0,"resolving":0,"restoring":0,"building":0,"integration":0,"storing":0,"additionalResolving":0,"additionalIntegration":0,"factory":0,"dependencies":0},"id":645,"issuerId":426,"chunks":[396],"assets":[],"reasons":[{"moduleIdentifier":"/home/stefan/Documents/Proyectos/interactive-pricing-component-main/node_modules/css-loader/dist/cjs.js!/home/stefan/Documents/Proyectos/interactive-pricing-component-main/src/style.css","module":"./node_modules/css-loader/dist/cjs.js!./src/style.css","moduleName":"./node_modules/css-loader/dist/cjs.js!./src/style.css","resolvedModuleIdentifier":"/home/stefan/Documents/Proyectos/interactive-pricing-component-main/node_modules/css-loader/dist/cjs.js!/home/stefan/Documents/Proyectos/interactive-pricing-component-main/src/style.css","resolvedModule":"./node_modules/css-loader/dist/cjs.js!./src/style.css","type":"harmony side effect evaluation","active":true,"explanation":"","userRequest":"../node_modules/css-loader/dist/runtime/api.js","loc":"2:0-89","moduleId":426,"resolvedModuleId":426},{"moduleIdentifier":"/home/stefan/Documents/Proyectos/interactive-pricing-component-main/node_modules/css-loader/dist/cjs.js!/home/stefan/Documents/Proyectos/interactive-pricing-component-main/src/style.css","module":"./node_modules/css-loader/dist/cjs.js!./src/style.css","moduleName":"./node_modules/css-loader/dist/cjs.js!./src/style.css","resolvedModuleIdentifier":"/home/stefan/Documents/Proyectos/interactive-pricing-component-main/node_modules/css-loader/dist/cjs.js!/home/stefan/Documents/Proyectos/interactive-pricing-component-main/src/style.css","resolvedModule":"./node_modules/css-loader/dist/cjs.js!./src/style.css","type":"harmony import specifier","active":true,"explanation":"","userRequest":"../node_modules/css-loader/dist/runtime/api.js","loc":"7:30-57","moduleId":426,"resolvedModuleId":426},{"moduleIdentifier":"/home/stefan/Documents/Proyectos/interactive-pricing-component-main/node_modules/css-loader/dist/runtime/api.js","module":"./node_modules/css-loader/dist/runtime/api.js","moduleName":"./node_modules/css-loader/dist/runtime/api.js","resolvedModuleIdentifier":"/home/stefan/Documents/Proyectos/interactive-pricing-component-main/node_modules/css-loader/dist/runtime/api.js","resolvedModule":"./node_modules/css-loader/dist/runtime/api.js","type":"cjs self exports reference","active":true,"explanation":"","userRequest":null,"loc":"9:0-14","moduleId":645,"resolvedModuleId":645}],"usedExports":null,"providedExports":null,"optimizationBailout":["CommonJS bailout: module.exports is used directly at 9:0-14","Statement (ExpressionStatement) with side effects in source code at 9:0-66:2","ModuleConcatenation bailout: Module is not an ECMAScript module"],"depth":1},{"type":"module","moduleType":"javascript/auto","layer":null,"size":817,"sizes":{"javascript":817},"built":true,"codeGenerated":true,"buildTimeExecuted":false,"cached":false,"identifier":"/home/stefan/Documents/Proyectos/interactive-pricing-component-main/node_modules/css-loader/dist/runtime/getUrl.js","name":"./node_modules/css-loader/dist/runtime/getUrl.js","nameForCondition":"/home/stefan/Documents/Proyectos/interactive-pricing-component-main/node_modules/css-loader/dist/runtime/getUrl.js","index":2,"preOrderIndex":2,"index2":1,"postOrderIndex":1,"cacheable":true,"optional":false,"orphan":false,"dependent":true,"issuer":"/home/stefan/Documents/Proyectos/interactive-pricing-component-main/node_modules/css-loader/dist/cjs.js!/home/stefan/Documents/Proyectos/interactive-pricing-component-main/src/style.css","issuerName":"./node_modules/css-loader/dist/cjs.js!./src/style.css","issuerPath":[{"identifier":"/home/stefan/Documents/Proyectos/interactive-pricing-component-main/node_modules/css-loader/dist/cjs.js!/home/stefan/Documents/Proyectos/interactive-pricing-component-main/src/style.css","name":"./node_modules/css-loader/dist/cjs.js!./src/style.css","profile":{"total":157,"resolving":7,"restoring":0,"building":150,"integration":0,"storing":0,"additionalResolving":0,"additionalIntegration":0,"factory":7,"dependencies":0},"id":426}],"failed":false,"errors":0,"warnings":0,"profile":{"total":0,"resolving":0,"restoring":0,"building":0,"integration":0,"storing":0,"additionalResolving":0,"additionalIntegration":0,"factory":0,"dependencies":0},"id":667,"issuerId":426,"chunks":[396],"assets":[],"reasons":[{"moduleIdentifier":"/home/stefan/Documents/Proyectos/interactive-pricing-component-main/node_modules/css-loader/dist/cjs.js!/home/stefan/Documents/Proyectos/interactive-pricing-component-main/src/style.css","module":"./node_modules/css-loader/dist/cjs.js!./src/style.css","moduleName":"./node_modules/css-loader/dist/cjs.js!./src/style.css","resolvedModuleIdentifier":"/home/stefan/Documents/Proyectos/interactive-pricing-component-main/node_modules/css-loader/dist/cjs.js!/home/stefan/Documents/Proyectos/interactive-pricing-component-main/src/style.css","resolvedModule":"./node_modules/css-loader/dist/cjs.js!./src/style.css","type":"harmony side effect evaluation","active":true,"explanation":"","userRequest":"../node_modules/css-loader/dist/runtime/getUrl.js","loc":"3:0-96","moduleId":426,"resolvedModuleId":426},{"moduleIdentifier":"/home/stefan/Documents/Proyectos/interactive-pricing-component-main/node_modules/css-loader/dist/cjs.js!/home/stefan/Documents/Proyectos/interactive-pricing-component-main/src/style.css","module":"./node_modules/css-loader/dist/cjs.js!./src/style.css","moduleName":"./node_modules/css-loader/dist/cjs.js!./src/style.css","resolvedModuleIdentifier":"/home/stefan/Documents/Proyectos/interactive-pricing-component-main/node_modules/css-loader/dist/cjs.js!/home/stefan/Documents/Proyectos/interactive-pricing-component-main/src/style.css","resolvedModule":"./node_modules/css-loader/dist/cjs.js!./src/style.css","type":"harmony import specifier","active":true,"explanation":"","userRequest":"../node_modules/css-loader/dist/runtime/getUrl.js","loc":"8:41-72","moduleId":426,"resolvedModuleId":426},{"moduleIdentifier":"/home/stefan/Documents/Proyectos/interactive-pricing-component-main/node_modules/css-loader/dist/cjs.js!/home/stefan/Documents/Proyectos/interactive-pricing-component-main/src/style.css","module":"./node_modules/css-loader/dist/cjs.js!./src/style.css","moduleName":"./node_modules/css-loader/dist/cjs.js!./src/style.css","resolvedModuleIdentifier":"/home/stefan/Documents/Proyectos/interactive-pricing-component-main/node_modules/css-loader/dist/cjs.js!/home/stefan/Documents/Proyectos/interactive-pricing-component-main/src/style.css","resolvedModule":"./node_modules/css-loader/dist/cjs.js!./src/style.css","type":"harmony import specifier","active":true,"explanation":"","userRequest":"../node_modules/css-loader/dist/runtime/getUrl.js","loc":"9:41-72","moduleId":426,"resolvedModuleId":426},{"moduleIdentifier":"/home/stefan/Documents/Proyectos/interactive-pricing-component-main/node_modules/css-loader/dist/cjs.js!/home/stefan/Documents/Proyectos/interactive-pricing-component-main/src/style.css","module":"./node_modules/css-loader/dist/cjs.js!./src/style.css","moduleName":"./node_modules/css-loader/dist/cjs.js!./src/style.css","resolvedModuleIdentifier":"/home/stefan/Documents/Proyectos/interactive-pricing-component-main/node_modules/css-loader/dist/cjs.js!/home/stefan/Documents/Proyectos/interactive-pricing-component-main/src/style.css","resolvedModule":"./node_modules/css-loader/dist/cjs.js!./src/style.css","type":"harmony import specifier","active":true,"explanation":"","userRequest":"../node_modules/css-loader/dist/runtime/getUrl.js","loc":"10:41-72","moduleId":426,"resolvedModuleId":426},{"moduleIdentifier":"/home/stefan/Documents/Proyectos/interactive-pricing-component-main/node_modules/css-loader/dist/runtime/getUrl.js","module":"./node_modules/css-loader/dist/runtime/getUrl.js","moduleName":"./node_modules/css-loader/dist/runtime/getUrl.js","resolvedModuleIdentifier":"/home/stefan/Documents/Proyectos/interactive-pricing-component-main/node_modules/css-loader/dist/runtime/getUrl.js","resolvedModule":"./node_modules/css-loader/dist/runtime/getUrl.js","type":"cjs self exports reference","active":true,"explanation":"","userRequest":null,"loc":"3:0-14","moduleId":667,"resolvedModuleId":667}],"usedExports":null,"providedExports":null,"optimizationBailout":["CommonJS bailout: module.exports is used directly at 3:0-14","Statement (ExpressionStatement) with side effects in source code at 3:0-33:2","ModuleConcatenation bailout: Module is not an ECMAScript module"],"depth":1},{"type":"module","moduleType":"runtime","layer":null,"size":267,"sizes":{"runtime":267},"built":false,"codeGenerated":true,"buildTimeExecuted":false,"cached":false,"identifier":"webpack/runtime/compat get default export","name":"webpack/runtime/compat get default export","nameForCondition":null,"index":null,"preOrderIndex":null,"index2":null,"postOrderIndex":null,"optional":false,"orphan":false,"dependent":false,"failed":false,"errors":0,"warnings":0,"id":"","chunks":[396],"assets":[],"reasons":[],"usedExports":null,"providedExports":[],"optimizationBailout":[],"depth":null},{"type":"module","moduleType":"runtime","layer":null,"size":308,"sizes":{"runtime":308},"built":false,"codeGenerated":true,"buildTimeExecuted":false,"cached":false,"identifier":"webpack/runtime/define property getters","name":"webpack/runtime/define property getters","nameForCondition":null,"index":null,"preOrderIndex":null,"index2":null,"postOrderIndex":null,"optional":false,"orphan":false,"dependent":false,"failed":false,"errors":0,"warnings":0,"id":"","chunks":[396],"assets":[],"reasons":[],"usedExports":null,"providedExports":[],"optimizationBailout":[],"depth":null},{"type":"module","moduleType":"runtime","layer":null,"size":88,"sizes":{"runtime":88},"built":false,"codeGenerated":true,"buildTimeExecuted":false,"cached":false,"identifier":"webpack/runtime/hasOwnProperty shorthand","name":"webpack/runtime/hasOwnProperty shorthand","nameForCondition":null,"index":null,"preOrderIndex":null,"index2":null,"postOrderIndex":null,"optional":false,"orphan":false,"dependent":false,"failed":false,"errors":0,"warnings":0,"id":"","chunks":[396],"assets":[],"reasons":[],"usedExports":null,"providedExports":[],"optimizationBailout":[],"depth":null},{"type":"module","moduleType":"runtime","layer":null,"size":274,"sizes":{"runtime":274},"built":false,"codeGenerated":true,"buildTimeExecuted":false,"cached":false,"identifier":"webpack/runtime/make namespace object","name":"webpack/runtime/make namespace object","nameForCondition":null,"index":null,"preOrderIndex":null,"index2":null,"postOrderIndex":null,"optional":false,"orphan":false,"dependent":false,"failed":false,"errors":0,"warnings":0,"id":"","chunks":[396],"assets":[],"reasons":[],"usedExports":null,"providedExports":[],"optimizationBailout":[],"depth":null},{"type":"module","moduleType":"runtime","layer":null,"size":66,"sizes":{"runtime":66},"built":false,"codeGenerated":true,"buildTimeExecuted":false,"cached":false,"identifier":"webpack/runtime/publicPath","name":"webpack/runtime/publicPath","nameForCondition":null,"index":null,"preOrderIndex":null,"index2":null,"postOrderIndex":null,"optional":false,"orphan":false,"dependent":false,"failed":false,"errors":0,"warnings":0,"id":"","chunks":[396],"assets":[],"reasons":[],"usedExports":null,"providedExports":[],"optimizationBailout":[],"depth":null},{"type":"module","moduleType":"runtime","layer":null,"size":500,"sizes":{"runtime":500},"built":false,"codeGenerated":true,"buildTimeExecuted":false,"cached":false,"identifier":"webpack/runtime/relative url","name":"webpack/runtime/relative url","nameForCondition":null,"index":null,"preOrderIndex":null,"index2":null,"postOrderIndex":null,"optional":false,"orphan":false,"dependent":false,"failed":false,"errors":0,"warnings":0,"id":"","chunks":[396],"assets":[],"reasons":[],"usedExports":null,"providedExports":[],"optimizationBailout":[],"depth":null}],"origins":[{"module":"","moduleIdentifier":"","moduleName":"","loc":"child","request":"!!/home/stefan/Documents/Proyectos/interactive-pricing-component-main/node_modules/css-loader/dist/cjs.js!/home/stefan/Documents/Proyectos/interactive-pricing-component-main/src/style.css"}]}],"modules":[{"type":"module","moduleType":"javascript/auto","layer":null,"size":5213,"sizes":{"javascript":5213},"built":true,"codeGenerated":true,"buildTimeExecuted":false,"cached":false,"identifier":"/home/stefan/Documents/Proyectos/interactive-pricing-component-main/node_modules/css-loader/dist/cjs.js!/home/stefan/Documents/Proyectos/interactive-pricing-component-main/src/style.css","name":"./node_modules/css-loader/dist/cjs.js!./src/style.css","nameForCondition":"/home/stefan/Documents/Proyectos/interactive-pricing-component-main/src/style.css","index":0,"preOrderIndex":0,"index2":5,"postOrderIndex":5,"cacheable":true,"optional":false,"orphan":false,"issuer":null,"issuerName":null,"issuerPath":null,"failed":false,"errors":0,"warnings":0,"profile":{"total":157,"resolving":7,"restoring":0,"building":150,"integration":0,"storing":0,"additionalResolving":0,"additionalIntegration":0,"factory":7,"dependencies":0},"id":426,"issuerId":null,"chunks":[396],"assets":[],"reasons":[{"moduleIdentifier":null,"module":null,"moduleName":null,"resolvedModuleIdentifier":null,"resolvedModule":null,"type":"entry","active":true,"explanation":"","userRequest":"!!/home/stefan/Documents/Proyectos/interactive-pricing-component-main/node_modules/css-loader/dist/cjs.js!/home/stefan/Documents/Proyectos/interactive-pricing-component-main/src/style.css","loc":"child","moduleId":null,"resolvedModuleId":null},{"moduleIdentifier":null,"module":null,"moduleName":null,"resolvedModuleIdentifier":null,"resolvedModule":null,"type":null,"active":true,"explanation":"used as library export","userRequest":null,"moduleId":null,"resolvedModuleId":null}],"usedExports":true,"providedExports":["default"],"optimizationBailout":["Statement (VariableDeclaration) with side effects in source code at 7:0-84","ModuleConcatenation bailout: Module uses module.id"],"depth":0},{"type":"module","moduleType":"javascript/auto","layer":null,"size":1605,"sizes":{"javascript":1605},"built":true,"codeGenerated":true,"buildTimeExecuted":false,"cached":false,"identifier":"/home/stefan/Documents/Proyectos/interactive-pricing-component-main/node_modules/css-loader/dist/runtime/api.js","name":"./node_modules/css-loader/dist/runtime/api.js","nameForCondition":"/home/stefan/Documents/Proyectos/interactive-pricing-component-main/node_modules/css-loader/dist/runtime/api.js","index":1,"preOrderIndex":1,"index2":0,"postOrderIndex":0,"cacheable":true,"optional":false,"orphan":false,"issuer":"/home/stefan/Documents/Proyectos/interactive-pricing-component-main/node_modules/css-loader/dist/cjs.js!/home/stefan/Documents/Proyectos/interactive-pricing-component-main/src/style.css","issuerName":"./node_modules/css-loader/dist/cjs.js!./src/style.css","issuerPath":[{"identifier":"/home/stefan/Documents/Proyectos/interactive-pricing-component-main/node_modules/css-loader/dist/cjs.js!/home/stefan/Documents/Proyectos/interactive-pricing-component-main/src/style.css","name":"./node_modules/css-loader/dist/cjs.js!./src/style.css","profile":{"total":157,"resolving":7,"restoring":0,"building":150,"integration":0,"storing":0,"additionalResolving":0,"additionalIntegration":0,"factory":7,"dependencies":0},"id":426}],"failed":false,"errors":0,"warnings":0,"profile":{"total":0,"resolving":0,"restoring":0,"building":0,"integration":0,"storing":0,"additionalResolving":0,"additionalIntegration":0,"factory":0,"dependencies":0},"id":645,"issuerId":426,"chunks":[396],"assets":[],"reasons":[{"moduleIdentifier":"/home/stefan/Documents/Proyectos/interactive-pricing-component-main/node_modules/css-loader/dist/cjs.js!/home/stefan/Documents/Proyectos/interactive-pricing-component-main/src/style.css","module":"./node_modules/css-loader/dist/cjs.js!./src/style.css","moduleName":"./node_modules/css-loader/dist/cjs.js!./src/style.css","resolvedModuleIdentifier":"/home/stefan/Documents/Proyectos/interactive-pricing-component-main/node_modules/css-loader/dist/cjs.js!/home/stefan/Documents/Proyectos/interactive-pricing-component-main/src/style.css","resolvedModule":"./node_modules/css-loader/dist/cjs.js!./src/style.css","type":"harmony side effect evaluation","active":true,"explanation":"","userRequest":"../node_modules/css-loader/dist/runtime/api.js","loc":"2:0-89","moduleId":426,"resolvedModuleId":426},{"moduleIdentifier":"/home/stefan/Documents/Proyectos/interactive-pricing-component-main/node_modules/css-loader/dist/cjs.js!/home/stefan/Documents/Proyectos/interactive-pricing-component-main/src/style.css","module":"./node_modules/css-loader/dist/cjs.js!./src/style.css","moduleName":"./node_modules/css-loader/dist/cjs.js!./src/style.css","resolvedModuleIdentifier":"/home/stefan/Documents/Proyectos/interactive-pricing-component-main/node_modules/css-loader/dist/cjs.js!/home/stefan/Documents/Proyectos/interactive-pricing-component-main/src/style.css","resolvedModule":"./node_modules/css-loader/dist/cjs.js!./src/style.css","type":"harmony import specifier","active":true,"explanation":"","userRequest":"../node_modules/css-loader/dist/runtime/api.js","loc":"7:30-57","moduleId":426,"resolvedModuleId":426},{"moduleIdentifier":"/home/stefan/Documents/Proyectos/interactive-pricing-component-main/node_modules/css-loader/dist/runtime/api.js","module":"./node_modules/css-loader/dist/runtime/api.js","moduleName":"./node_modules/css-loader/dist/runtime/api.js","resolvedModuleIdentifier":"/home/stefan/Documents/Proyectos/interactive-pricing-component-main/node_modules/css-loader/dist/runtime/api.js","resolvedModule":"./node_modules/css-loader/dist/runtime/api.js","type":"cjs self exports reference","active":true,"explanation":"","userRequest":null,"loc":"9:0-14","moduleId":645,"resolvedModuleId":645}],"usedExports":null,"providedExports":null,"optimizationBailout":["CommonJS bailout: module.exports is used directly at 9:0-14","Statement (ExpressionStatement) with side effects in source code at 9:0-66:2","ModuleConcatenation bailout: Module is not an ECMAScript module"],"depth":1},{"type":"module","moduleType":"javascript/auto","layer":null,"size":817,"sizes":{"javascript":817},"built":true,"codeGenerated":true,"buildTimeExecuted":false,"cached":false,"identifier":"/home/stefan/Documents/Proyectos/interactive-pricing-component-main/node_modules/css-loader/dist/runtime/getUrl.js","name":"./node_modules/css-loader/dist/runtime/getUrl.js","nameForCondition":"/home/stefan/Documents/Proyectos/interactive-pricing-component-main/node_modules/css-loader/dist/runtime/getUrl.js","index":2,"preOrderIndex":2,"index2":1,"postOrderIndex":1,"cacheable":true,"optional":false,"orphan":false,"issuer":"/home/stefan/Documents/Proyectos/interactive-pricing-component-main/node_modules/css-loader/dist/cjs.js!/home/stefan/Documents/Proyectos/interactive-pricing-component-main/src/style.css","issuerName":"./node_modules/css-loader/dist/cjs.js!./src/style.css","issuerPath":[{"identifier":"/home/stefan/Documents/Proyectos/interactive-pricing-component-main/node_modules/css-loader/dist/cjs.js!/home/stefan/Documents/Proyectos/interactive-pricing-component-main/src/style.css","name":"./node_modules/css-loader/dist/cjs.js!./src/style.css","profile":{"total":157,"resolving":7,"restoring":0,"building":150,"integration":0,"storing":0,"additionalResolving":0,"additionalIntegration":0,"factory":7,"dependencies":0},"id":426}],"failed":false,"errors":0,"warnings":0,"profile":{"total":0,"resolving":0,"restoring":0,"building":0,"integration":0,"storing":0,"additionalResolving":0,"additionalIntegration":0,"factory":0,"dependencies":0},"id":667,"issuerId":426,"chunks":[396],"assets":[],"reasons":[{"moduleIdentifier":"/home/stefan/Documents/Proyectos/interactive-pricing-component-main/node_modules/css-loader/dist/cjs.js!/home/stefan/Documents/Proyectos/interactive-pricing-component-main/src/style.css","module":"./node_modules/css-loader/dist/cjs.js!./src/style.css","moduleName":"./node_modules/css-loader/dist/cjs.js!./src/style.css","resolvedModuleIdentifier":"/home/stefan/Documents/Proyectos/interactive-pricing-component-main/node_modules/css-loader/dist/cjs.js!/home/stefan/Documents/Proyectos/interactive-pricing-component-main/src/style.css","resolvedModule":"./node_modules/css-loader/dist/cjs.js!./src/style.css","type":"harmony side effect evaluation","active":true,"explanation":"","userRequest":"../node_modules/css-loader/dist/runtime/getUrl.js","loc":"3:0-96","moduleId":426,"resolvedModuleId":426},{"moduleIdentifier":"/home/stefan/Documents/Proyectos/interactive-pricing-component-main/node_modules/css-loader/dist/cjs.js!/home/stefan/Documents/Proyectos/interactive-pricing-component-main/src/style.css","module":"./node_modules/css-loader/dist/cjs.js!./src/style.css","moduleName":"./node_modules/css-loader/dist/cjs.js!./src/style.css","resolvedModuleIdentifier":"/home/stefan/Documents/Proyectos/interactive-pricing-component-main/node_modules/css-loader/dist/cjs.js!/home/stefan/Documents/Proyectos/interactive-pricing-component-main/src/style.css","resolvedModule":"./node_modules/css-loader/dist/cjs.js!./src/style.css","type":"harmony import specifier","active":true,"explanation":"","userRequest":"../node_modules/css-loader/dist/runtime/getUrl.js","loc":"8:41-72","moduleId":426,"resolvedModuleId":426},{"moduleIdentifier":"/home/stefan/Documents/Proyectos/interactive-pricing-component-main/node_modules/css-loader/dist/cjs.js!/home/stefan/Documents/Proyectos/interactive-pricing-component-main/src/style.css","module":"./node_modules/css-loader/dist/cjs.js!./src/style.css","moduleName":"./node_modules/css-loader/dist/cjs.js!./src/style.css","resolvedModuleIdentifier":"/home/stefan/Documents/Proyectos/interactive-pricing-component-main/node_modules/css-loader/dist/cjs.js!/home/stefan/Documents/Proyectos/interactive-pricing-component-main/src/style.css","resolvedModule":"./node_modules/css-loader/dist/cjs.js!./src/style.css","type":"harmony import specifier","active":true,"explanation":"","userRequest":"../node_modules/css-loader/dist/runtime/getUrl.js","loc":"9:41-72","moduleId":426,"resolvedModuleId":426},{"moduleIdentifier":"/home/stefan/Documents/Proyectos/interactive-pricing-component-main/node_modules/css-loader/dist/cjs.js!/home/stefan/Documents/Proyectos/interactive-pricing-component-main/src/style.css","module":"./node_modules/css-loader/dist/cjs.js!./src/style.css","moduleName":"./node_modules/css-loader/dist/cjs.js!./src/style.css","resolvedModuleIdentifier":"/home/stefan/Documents/Proyectos/interactive-pricing-component-main/node_modules/css-loader/dist/cjs.js!/home/stefan/Documents/Proyectos/interactive-pricing-component-main/src/style.css","resolvedModule":"./node_modules/css-loader/dist/cjs.js!./src/style.css","type":"harmony import specifier","active":true,"explanation":"","userRequest":"../node_modules/css-loader/dist/runtime/getUrl.js","loc":"10:41-72","moduleId":426,"resolvedModuleId":426},{"moduleIdentifier":"/home/stefan/Documents/Proyectos/interactive-pricing-component-main/node_modules/css-loader/dist/runtime/getUrl.js","module":"./node_modules/css-loader/dist/runtime/getUrl.js","moduleName":"./node_modules/css-loader/dist/runtime/getUrl.js","resolvedModuleIdentifier":"/home/stefan/Documents/Proyectos/interactive-pricing-component-main/node_modules/css-loader/dist/runtime/getUrl.js","resolvedModule":"./node_modules/css-loader/dist/runtime/getUrl.js","type":"cjs self exports reference","active":true,"explanation":"","userRequest":null,"loc":"3:0-14","moduleId":667,"resolvedModuleId":667}],"usedExports":null,"providedExports":null,"optimizationBailout":["CommonJS bailout: module.exports is used directly at 3:0-14","Statement (ExpressionStatement) with side effects in source code at 3:0-33:2","ModuleConcatenation bailout: Module is not an ECMAScript module"],"depth":1},{"type":"module","moduleType":"asset/resource","layer":null,"size":42,"sizes":{"javascript":42,"asset":170},"built":true,"codeGenerated":true,"buildTimeExecuted":false,"cached":false,"identifier":"asset/resource|/home/stefan/Documents/Proyectos/interactive-pricing-component-main/images/bg-pattern.svg","name":"./images/bg-pattern.svg","nameForCondition":"/home/stefan/Documents/Proyectos/interactive-pricing-component-main/images/bg-pattern.svg","index":3,"preOrderIndex":3,"index2":2,"postOrderIndex":2,"cacheable":true,"optional":false,"orphan":false,"issuer":"/home/stefan/Documents/Proyectos/interactive-pricing-component-main/node_modules/css-loader/dist/cjs.js!/home/stefan/Documents/Proyectos/interactive-pricing-component-main/src/style.css","issuerName":"./node_modules/css-loader/dist/cjs.js!./src/style.css","issuerPath":[{"identifier":"/home/stefan/Documents/Proyectos/interactive-pricing-component-main/node_modules/css-loader/dist/cjs.js!/home/stefan/Documents/Proyectos/interactive-pricing-component-main/src/style.css","name":"./node_modules/css-loader/dist/cjs.js!./src/style.css","profile":{"total":157,"resolving":7,"restoring":0,"building":150,"integration":0,"storing":0,"additionalResolving":0,"additionalIntegration":0,"factory":7,"dependencies":0},"id":426}],"failed":false,"errors":0,"warnings":0,"profile":{"total":37,"resolving":19,"restoring":0,"building":18,"integration":0,"storing":0,"additionalResolving":0,"additionalIntegration":0,"factory":19,"dependencies":0},"id":576,"issuerId":426,"chunks":[396],"assets":[],"reasons":[{"moduleIdentifier":"/home/stefan/Documents/Proyectos/interactive-pricing-component-main/node_modules/css-loader/dist/cjs.js!/home/stefan/Documents/Proyectos/interactive-pricing-component-main/src/style.css","module":"./node_modules/css-loader/dist/cjs.js!./src/style.css","moduleName":"./node_modules/css-loader/dist/cjs.js!./src/style.css","resolvedModuleIdentifier":"/home/stefan/Documents/Proyectos/interactive-pricing-component-main/node_modules/css-loader/dist/cjs.js!/home/stefan/Documents/Proyectos/interactive-pricing-component-main/src/style.css","resolvedModule":"./node_modules/css-loader/dist/cjs.js!./src/style.css","type":"new URL()","active":true,"explanation":"","userRequest":"../images/bg-pattern.svg","loc":"4:36-88","moduleId":426,"resolvedModuleId":426}],"usedExports":true,"providedExports":[],"optimizationBailout":["ModuleConcatenation bailout: Module Concatenation is not implemented for AssetGenerator"],"depth":1},{"type":"module","moduleType":"asset/resource","layer":null,"size":42,"sizes":{"javascript":42,"asset":196},"built":true,"codeGenerated":true,"buildTimeExecuted":false,"cached":false,"identifier":"asset/resource|/home/stefan/Documents/Proyectos/interactive-pricing-component-main/images/pattern-circles.svg","name":"./images/pattern-circles.svg","nameForCondition":"/home/stefan/Documents/Proyectos/interactive-pricing-component-main/images/pattern-circles.svg","index":4,"preOrderIndex":4,"index2":3,"postOrderIndex":3,"cacheable":true,"optional":false,"orphan":false,"issuer":"/home/stefan/Documents/Proyectos/interactive-pricing-component-main/node_modules/css-loader/dist/cjs.js!/home/stefan/Documents/Proyectos/interactive-pricing-component-main/src/style.css","issuerName":"./node_modules/css-loader/dist/cjs.js!./src/style.css","issuerPath":[{"identifier":"/home/stefan/Documents/Proyectos/interactive-pricing-component-main/node_modules/css-loader/dist/cjs.js!/home/stefan/Documents/Proyectos/interactive-pricing-component-main/src/style.css","name":"./node_modules/css-loader/dist/cjs.js!./src/style.css","profile":{"total":157,"resolving":7,"restoring":0,"building":150,"integration":0,"storing":0,"additionalResolving":0,"additionalIntegration":0,"factory":7,"dependencies":0},"id":426}],"failed":false,"errors":0,"warnings":0,"profile":{"total":37,"resolving":19,"restoring":0,"building":18,"integration":0,"storing":0,"additionalResolving":0,"additionalIntegration":0,"factory":19,"dependencies":0},"id":175,"issuerId":426,"chunks":[396],"assets":[],"reasons":[{"moduleIdentifier":"/home/stefan/Documents/Proyectos/interactive-pricing-component-main/node_modules/css-loader/dist/cjs.js!/home/stefan/Documents/Proyectos/interactive-pricing-component-main/src/style.css","module":"./node_modules/css-loader/dist/cjs.js!./src/style.css","moduleName":"./node_modules/css-loader/dist/cjs.js!./src/style.css","resolvedModuleIdentifier":"/home/stefan/Documents/Proyectos/interactive-pricing-component-main/node_modules/css-loader/dist/cjs.js!/home/stefan/Documents/Proyectos/interactive-pricing-component-main/src/style.css","resolvedModule":"./node_modules/css-loader/dist/cjs.js!./src/style.css","type":"new URL()","active":true,"explanation":"","userRequest":"../images/pattern-circles.svg","loc":"5:36-93","moduleId":426,"resolvedModuleId":426}],"usedExports":true,"providedExports":[],"optimizationBailout":["ModuleConcatenation bailout: Module Concatenation is not implemented for AssetGenerator"],"depth":1},{"type":"module","moduleType":"asset/resource","layer":null,"size":42,"sizes":{"javascript":42,"asset":153},"built":true,"codeGenerated":true,"buildTimeExecuted":false,"cached":false,"identifier":"asset/resource|/home/stefan/Documents/Proyectos/interactive-pricing-component-main/images/icon-check.svg","name":"./images/icon-check.svg","nameForCondition":"/home/stefan/Documents/Proyectos/interactive-pricing-component-main/images/icon-check.svg","index":5,"preOrderIndex":5,"index2":4,"postOrderIndex":4,"cacheable":true,"optional":false,"orphan":false,"issuer":"/home/stefan/Documents/Proyectos/interactive-pricing-component-main/node_modules/css-loader/dist/cjs.js!/home/stefan/Documents/Proyectos/interactive-pricing-component-main/src/style.css","issuerName":"./node_modules/css-loader/dist/cjs.js!./src/style.css","issuerPath":[{"identifier":"/home/stefan/Documents/Proyectos/interactive-pricing-component-main/node_modules/css-loader/dist/cjs.js!/home/stefan/Documents/Proyectos/interactive-pricing-component-main/src/style.css","name":"./node_modules/css-loader/dist/cjs.js!./src/style.css","profile":{"total":157,"resolving":7,"restoring":0,"building":150,"integration":0,"storing":0,"additionalResolving":0,"additionalIntegration":0,"factory":7,"dependencies":0},"id":426}],"failed":false,"errors":0,"warnings":0,"profile":{"total":38,"resolving":19,"restoring":0,"building":19,"integration":0,"storing":0,"additionalResolving":0,"additionalIntegration":0,"factory":19,"dependencies":0},"id":328,"issuerId":426,"chunks":[396],"assets":[],"reasons":[{"moduleIdentifier":"/home/stefan/Documents/Proyectos/interactive-pricing-component-main/node_modules/css-loader/dist/cjs.js!/home/stefan/Documents/Proyectos/interactive-pricing-component-main/src/style.css","module":"./node_modules/css-loader/dist/cjs.js!./src/style.css","moduleName":"./node_modules/css-loader/dist/cjs.js!./src/style.css","resolvedModuleIdentifier":"/home/stefan/Documents/Proyectos/interactive-pricing-component-main/node_modules/css-loader/dist/cjs.js!/home/stefan/Documents/Proyectos/interactive-pricing-component-main/src/style.css","resolvedModule":"./node_modules/css-loader/dist/cjs.js!./src/style.css","type":"new URL()","active":true,"explanation":"","userRequest":"../images/icon-check.svg","loc":"6:36-88","moduleId":426,"resolvedModuleId":426}],"usedExports":true,"providedExports":[],"optimizationBailout":["ModuleConcatenation bailout: Module Concatenation is not implemented for AssetGenerator"],"depth":1},{"type":"module","moduleType":"runtime","layer":null,"size":267,"sizes":{"runtime":267},"built":false,"codeGenerated":true,"buildTimeExecuted":false,"cached":false,"identifier":"webpack/runtime/compat get default export","name":"webpack/runtime/compat get default export","nameForCondition":null,"index":null,"preOrderIndex":null,"index2":null,"postOrderIndex":null,"optional":false,"orphan":false,"failed":false,"errors":0,"warnings":0,"id":"","chunks":[396],"assets":[],"reasons":[],"usedExports":null,"providedExports":[],"optimizationBailout":[],"depth":null},{"type":"module","moduleType":"runtime","layer":null,"size":308,"sizes":{"runtime":308},"built":false,"codeGenerated":true,"buildTimeExecuted":false,"cached":false,"identifier":"webpack/runtime/define property getters","name":"webpack/runtime/define property getters","nameForCondition":null,"index":null,"preOrderIndex":null,"index2":null,"postOrderIndex":null,"optional":false,"orphan":false,"failed":false,"errors":0,"warnings":0,"id":"","chunks":[396],"assets":[],"reasons":[],"usedExports":null,"providedExports":[],"optimizationBailout":[],"depth":null},{"type":"module","moduleType":"runtime","layer":null,"size":88,"sizes":{"runtime":88},"built":false,"codeGenerated":true,"buildTimeExecuted":false,"cached":false,"identifier":"webpack/runtime/hasOwnProperty shorthand","name":"webpack/runtime/hasOwnProperty shorthand","nameForCondition":null,"index":null,"preOrderIndex":null,"index2":null,"postOrderIndex":null,"optional":false,"orphan":false,"failed":false,"errors":0,"warnings":0,"id":"","chunks":[396],"assets":[],"reasons":[],"usedExports":null,"providedExports":[],"optimizationBailout":[],"depth":null},{"type":"module","moduleType":"runtime","layer":null,"size":274,"sizes":{"runtime":274},"built":false,"codeGenerated":true,"buildTimeExecuted":false,"cached":false,"identifier":"webpack/runtime/make namespace object","name":"webpack/runtime/make namespace object","nameForCondition":null,"index":null,"preOrderIndex":null,"index2":null,"postOrderIndex":null,"optional":false,"orphan":false,"failed":false,"errors":0,"warnings":0,"id":"","chunks":[396],"assets":[],"reasons":[],"usedExports":null,"providedExports":[],"optimizationBailout":[],"depth":null},{"type":"module","moduleType":"runtime","layer":null,"size":66,"sizes":{"runtime":66},"built":false,"codeGenerated":true,"buildTimeExecuted":false,"cached":false,"identifier":"webpack/runtime/publicPath","name":"webpack/runtime/publicPath","nameForCondition":null,"index":null,"preOrderIndex":null,"index2":null,"postOrderIndex":null,"optional":false,"orphan":false,"failed":false,"errors":0,"warnings":0,"id":"","chunks":[396],"assets":[],"reasons":[],"usedExports":null,"providedExports":[],"optimizationBailout":[],"depth":null},{"type":"module","moduleType":"runtime","layer":null,"size":500,"sizes":{"runtime":500},"built":false,"codeGenerated":true,"buildTimeExecuted":false,"cached":false,"identifier":"webpack/runtime/relative url","name":"webpack/runtime/relative url","nameForCondition":null,"index":null,"preOrderIndex":null,"index2":null,"postOrderIndex":null,"optional":false,"orphan":false,"failed":false,"errors":0,"warnings":0,"id":"","chunks":[396],"assets":[],"reasons":[],"usedExports":null,"providedExports":[],"optimizationBailout":[],"depth":null}],"entrypoints":{"child":{"name":"child","chunks":[396],"assets":[],"filteredAssets":0,"assetsSize":0,"auxiliaryAssets":[{"name":"76d3fa7ddce078ad96b5.svg"},{"name":"83c38a48815855ecc2d7.svg"},{"name":"9f6ed14bb3b0084b05a9.svg"}],"filteredAuxiliaryAssets":0,"auxiliaryAssetsSize":null,"children":{},"childAssets":{},"isOverSizeLimit":false}},"namedChunkGroups":{"child":{"name":"child","chunks":[396],"assets":[],"filteredAssets":0,"assetsSize":0,"auxiliaryAssets":[{"name":"76d3fa7ddce078ad96b5.svg"},{"name":"83c38a48815855ecc2d7.svg"},{"name":"9f6ed14bb3b0084b05a9.svg"}],"filteredAuxiliaryAssets":0,"auxiliaryAssetsSize":null,"children":{},"childAssets":{},"isOverSizeLimit":false}},"errors":[],"errorsCount":0,"warnings":[],"warningsCount":0,"children":[]}]}